functional/__init__.py
functional/anyval.py
functional/builtins_wrapper.py
functional/chaintools.py
functional/containers.py
functional/filters.py
functional/final.py
functional/monads.py
functional/option.py
functional/predef.py
functional/typing_wrapper.py
functional/util.py
functional_python-0.3.1.dist-info/LICENSE
functional_python-0.3.1.dist-info/METADATA
functional_python-0.3.1.dist-info/WHEEL
functional_python-0.3.1.dist-info/top_level.txt
functional_python-0.3.1.dist-info/RECORD
