Metadata-Version: 2.1
Name: functional-python
Version: 0.3.1
Summary: Python implementation of Scala-like monadic data types.
Home-page: https://gitlab.com/Hares-Lab/libraries/functional-python
Author: Peter Zaitcev / USSX Hares
Maintainer: Peter Zaitcev / USSX Hares
License: BSD 2-clause
Platform: UNKNOWN
Classifier: Development Status :: 2 - Pre-Alpha
Classifier: License :: OSI Approved :: BSD License
Classifier: Intended Audience :: Developers
Classifier: Natural Language :: English
Classifier: Operating System :: OS Independent
Classifier: Programming Language :: Python :: 3.6
Classifier: Programming Language :: Python :: 3.7
Classifier: Programming Language :: Python :: 3.8
Classifier: Programming Language :: Python :: 3.9
Classifier: Topic :: Internet
Classifier: Topic :: Software Development :: Libraries
Classifier: Topic :: Software Development :: Libraries :: Python Modules
Classifier: Topic :: Utilities
License-File: LICENSE
Requires-Dist: typing-extensions (~=3.10.0) ; python_version < "3.9"
Requires-Dist: dataclasses (~=0.6) ; python_version == "3.6"
Requires-Dist: typing-inspect (~=0.7.1) ; python_version == "3.6"
Provides-Extra: all
Requires-Dist: cacheable-iterators (~=0.1.1) ; extra == 'all'
Requires-Dist: dataclasses-json (~=0.5.4) ; extra == 'all'
Requires-Dist: lxml (~=4.6.3) ; extra == 'all'
Requires-Dist: unittest-xml-reporting (~=3.0.4) ; extra == 'all'
Provides-Extra: test
Requires-Dist: cacheable-iterators (~=0.1.1) ; extra == 'test'
Requires-Dist: dataclasses-json (~=0.5.4) ; extra == 'test'
Requires-Dist: lxml (~=4.6.3) ; extra == 'test'
Requires-Dist: unittest-xml-reporting (~=3.0.4) ; extra == 'test'
